blowpipe/App.py
blowpipe/__init__.py
blowpipe/__main__.py
blowpipe/bootstrap.py
blowpipe/bp_utils.py
blowpipe/client_cli.py
blowpipe/client_grpc.py
blowpipe/config.py
blowpipe/constants.py
blowpipe/docker_utils.py
blowpipe/exceptions.py
blowpipe/flask_api.py
blowpipe/logger.py
blowpipe/model.py
blowpipe/model_db.py
blowpipe/model_state.py
blowpipe/scheduler.py
blowpipe/server.py
blowpipe/server_flask.py
blowpipe/server_grpc.py
blowpipe/tail.py
blowpipe/protos/__init__.py
blowpipe/protos/objects_pb2.py
blowpipe/protos/objects_pb2_grpc.py
blowpipe/protos/services_pb2.py
blowpipe/protos/services_pb2_grpc.py
blowpipe-0.0.8.dist-info/LICENSE.txt
blowpipe-0.0.8.dist-info/METADATA
blowpipe-0.0.8.dist-info/WHEEL
blowpipe-0.0.8.dist-info/entry_points.txt
blowpipe-0.0.8.dist-info/top_level.txt
blowpipe-0.0.8.dist-info/RECORD
